{"abstract":[{"type":"text","text":"Applies Lockman locking to effects with support for nested actions (3 paths)."}],"identifier":{"interfaceLanguage":"swift","url":"doc:\/\/Lockman\/documentation\/Lockman\/LockmanDynamicConditionReducer\/lock(boundaryId:unlockOption:lockFailure:for:_:_:)"},"primaryContentSections":[{"declarations":[{"platforms":["macOS"],"languages":["swift"],"tokens":[{"kind":"keyword","text":"func"},{"kind":"text","text":" "},{"kind":"identifier","text":"lock"},{"kind":"text","text":"<"},{"kind":"genericParameter","text":"Value1"},{"kind":"text","text":", "},{"kind":"genericParameter","text":"Value2"},{"kind":"text","text":", "},{"kind":"genericParameter","text":"Value3"},{"kind":"text","text":">("},{"kind":"externalParam","text":"boundaryId"},{"text":": any ","kind":"text"},{"text":"LockmanBoundaryId","kind":"typeIdentifier","identifier":"doc:\/\/Lockman\/documentation\/Lockman\/LockmanBoundaryId","preciseIdentifier":"s:7Lockman0A10BoundaryIda"},{"text":", ","kind":"text"},{"text":"unlockOption","kind":"externalParam"},{"text":": ","kind":"text"},{"text":"LockmanUnlockOption","kind":"typeIdentifier","identifier":"doc:\/\/Lockman\/documentation\/Lockman\/LockmanUnlockOption","preciseIdentifier":"s:7Lockman0A12UnlockOptionO"},{"text":" = .immediate, ","kind":"text"},{"text":"lockFailure","kind":"externalParam"},{"text":": ((any ","kind":"text"},{"text":"Error","kind":"typeIdentifier","preciseIdentifier":"s:s5ErrorP"},{"kind":"text","text":", "},{"preciseIdentifier":"s:22ComposableArchitecture4SendV","kind":"typeIdentifier","text":"Send"},{"kind":"text","text":"<"},{"kind":"typeIdentifier","text":"Self"},{"kind":"text","text":"."},{"preciseIdentifier":"s:22ComposableArchitecture7ReducerP6ActionQa","kind":"typeIdentifier","text":"Action"},{"kind":"text","text":">) "},{"kind":"keyword","text":"async"},{"kind":"text","text":" -> "},{"preciseIdentifier":"s:s4Voida","kind":"typeIdentifier","text":"Void"},{"kind":"text","text":")? = nil, "},{"kind":"externalParam","text":"for"},{"kind":"text","text":" "},{"kind":"internalParam","text":"path1"},{"kind":"text","text":": "},{"preciseIdentifier":"s:13CasePathsCore0A7KeyPatha","kind":"typeIdentifier","text":"CaseKeyPath"},{"kind":"text","text":"<"},{"kind":"typeIdentifier","text":"Self"},{"kind":"text","text":"."},{"preciseIdentifier":"s:22ComposableArchitecture7ReducerP6ActionQa","kind":"typeIdentifier","text":"Action"},{"kind":"text","text":", "},{"kind":"typeIdentifier","text":"Value1"},{"kind":"text","text":">, "},{"kind":"externalParam","text":"_"},{"kind":"text","text":" "},{"kind":"internalParam","text":"path2"},{"kind":"text","text":": "},{"preciseIdentifier":"s:13CasePathsCore0A7KeyPatha","kind":"typeIdentifier","text":"CaseKeyPath"},{"kind":"text","text":"<"},{"kind":"typeIdentifier","text":"Self"},{"kind":"text","text":"."},{"preciseIdentifier":"s:22ComposableArchitecture7ReducerP6ActionQa","kind":"typeIdentifier","text":"Action"},{"kind":"text","text":", "},{"kind":"typeIdentifier","text":"Value2"},{"kind":"text","text":">, "},{"kind":"externalParam","text":"_"},{"kind":"text","text":" "},{"kind":"internalParam","text":"path3"},{"kind":"text","text":": "},{"preciseIdentifier":"s:13CasePathsCore0A7KeyPatha","kind":"typeIdentifier","text":"CaseKeyPath"},{"kind":"text","text":"<"},{"kind":"typeIdentifier","text":"Self"},{"kind":"text","text":"."},{"preciseIdentifier":"s:22ComposableArchitecture7ReducerP6ActionQa","kind":"typeIdentifier","text":"Action"},{"kind":"text","text":", "},{"kind":"typeIdentifier","text":"Value3"},{"kind":"text","text":">) -> "},{"preciseIdentifier":"s:7Lockman0A7ReducerV","kind":"typeIdentifier","identifier":"doc:\/\/Lockman\/documentation\/Lockman\/LockmanReducer","text":"LockmanReducer"},{"kind":"text","text":"<"},{"kind":"typeIdentifier","text":"Self"},{"kind":"text","text":"> "},{"kind":"keyword","text":"where"},{"kind":"text","text":" "},{"kind":"typeIdentifier","text":"Self"},{"kind":"text","text":"."},{"preciseIdentifier":"s:22ComposableArchitecture7ReducerP6ActionQa","kind":"typeIdentifier","text":"Action"},{"kind":"text","text":" : "},{"preciseIdentifier":"s:13CasePathsCore0A8PathableP","kind":"typeIdentifier","text":"CasePathable"}]}],"kind":"declarations"},{"parameters":[{"content":[{"type":"paragraph","inlineContent":[{"text":"The boundary identifier for locking.","type":"text"}]}],"name":"boundaryId"},{"content":[{"inlineContent":[{"type":"text","text":"When to release the lock. Defaults to "},{"type":"codeVoice","code":".immediate"},{"type":"text","text":"."}],"type":"paragraph"}],"name":"unlockOption"},{"content":[{"inlineContent":[{"type":"text","text":"Optional callback invoked when lock acquisition fails."}],"type":"paragraph"}],"name":"lockFailure"},{"content":[{"type":"paragraph","inlineContent":[{"text":"First case path to extract a nested action.","type":"text"}]}],"name":"path1"},{"content":[{"type":"paragraph","inlineContent":[{"type":"text","text":"Second case path to extract a nested action."}]}],"name":"path2"},{"content":[{"inlineContent":[{"type":"text","text":"Third case path to extract a nested action."}],"type":"paragraph"}],"name":"path3"}],"kind":"parameters"},{"content":[{"anchor":"return-value","level":2,"type":"heading","text":"Return Value"},{"inlineContent":[{"type":"text","text":"A "},{"type":"codeVoice","code":"LockmanReducer"},{"type":"text","text":" that wraps this reducer with locking behavior."}],"type":"paragraph"}],"kind":"content"},{"content":[{"type":"heading","level":2,"anchor":"discussion","text":"Discussion"},{"type":"paragraph","inlineContent":[{"type":"text","text":"This overload supports the ViewAction pattern in TCA where actions may be nested"},{"type":"text","text":" "},{"type":"text","text":"within enum cases. It checks the root action and the specified nested paths."}]}],"kind":"content"}],"hierarchy":{"paths":[["doc:\/\/Lockman\/documentation\/Lockman","doc:\/\/Lockman\/documentation\/Lockman\/LockmanDynamicConditionReducer","doc:\/\/Lockman\/documentation\/Lockman\/LockmanDynamicConditionReducer\/Reducer-Implementations"]]},"metadata":{"extendedModule":"ComposableArchitecture","fragments":[{"text":"func","kind":"keyword"},{"text":" ","kind":"text"},{"text":"lock","kind":"identifier"},{"text":"<","kind":"text"},{"text":"Value1","kind":"genericParameter"},{"text":", ","kind":"text"},{"text":"Value2","kind":"genericParameter"},{"text":", ","kind":"text"},{"text":"Value3","kind":"genericParameter"},{"text":">(","kind":"text"},{"text":"boundaryId","kind":"externalParam"},{"text":": any ","kind":"text"},{"text":"LockmanBoundaryId","preciseIdentifier":"s:7Lockman0A10BoundaryIda","kind":"typeIdentifier"},{"text":", ","kind":"text"},{"text":"unlockOption","kind":"externalParam"},{"text":": ","kind":"text"},{"text":"LockmanUnlockOption","preciseIdentifier":"s:7Lockman0A12UnlockOptionO","kind":"typeIdentifier"},{"text":", ","kind":"text"},{"text":"lockFailure","kind":"externalParam"},{"text":": ((any ","kind":"text"},{"text":"Error","preciseIdentifier":"s:s5ErrorP","kind":"typeIdentifier"},{"text":", ","kind":"text"},{"text":"Send","preciseIdentifier":"s:22ComposableArchitecture4SendV","kind":"typeIdentifier"},{"text":"<","kind":"text"},{"text":"Self","kind":"typeIdentifier"},{"text":".","kind":"text"},{"text":"Action","preciseIdentifier":"s:22ComposableArchitecture7ReducerP6ActionQa","kind":"typeIdentifier"},{"text":">) ","kind":"text"},{"text":"async","kind":"keyword"},{"text":" -> ","kind":"text"},{"text":"Void","preciseIdentifier":"s:s4Voida","kind":"typeIdentifier"},{"text":")?, ","kind":"text"},{"text":"for","kind":"externalParam"},{"text":": ","kind":"text"},{"text":"CaseKeyPath","preciseIdentifier":"s:13CasePathsCore0A7KeyPatha","kind":"typeIdentifier"},{"text":"<","kind":"text"},{"text":"Self","kind":"typeIdentifier"},{"text":".","kind":"text"},{"text":"Action","preciseIdentifier":"s:22ComposableArchitecture7ReducerP6ActionQa","kind":"typeIdentifier"},{"text":", ","kind":"text"},{"text":"Value1","kind":"typeIdentifier"},{"text":">, ","kind":"text"},{"text":"CaseKeyPath","preciseIdentifier":"s:13CasePathsCore0A7KeyPatha","kind":"typeIdentifier"},{"text":"<","kind":"text"},{"text":"Self","kind":"typeIdentifier"},{"text":".","kind":"text"},{"text":"Action","preciseIdentifier":"s:22ComposableArchitecture7ReducerP6ActionQa","kind":"typeIdentifier"},{"text":", ","kind":"text"},{"text":"Value2","kind":"typeIdentifier"},{"text":">, ","kind":"text"},{"text":"CaseKeyPath","preciseIdentifier":"s:13CasePathsCore0A7KeyPatha","kind":"typeIdentifier"},{"text":"<","kind":"text"},{"text":"Self","kind":"typeIdentifier"},{"text":".","kind":"text"},{"text":"Action","preciseIdentifier":"s:22ComposableArchitecture7ReducerP6ActionQa","kind":"typeIdentifier"},{"text":", ","kind":"text"},{"text":"Value3","kind":"typeIdentifier"},{"text":">) -> ","kind":"text"},{"text":"LockmanReducer","preciseIdentifier":"s:7Lockman0A7ReducerV","kind":"typeIdentifier"},{"text":"<","kind":"text"},{"text":"Self","kind":"typeIdentifier"},{"text":">","kind":"text"}],"modules":[{"name":"Lockman","relatedModules":["ComposableArchitecture"]}],"role":"symbol","symbolKind":"method","title":"lock(boundaryId:unlockOption:lockFailure:for:_:_:)","roleHeading":"Instance Method","externalID":"s:22ComposableArchitecture7ReducerP7LockmanE4lock10boundaryId12unlockOption0E7Failure3for__AD0dC0VyxGSH_s8Sendablep_AD0d6UnlockI0Oys5Error_p_AA4SendVy6ActionQzGtYaYbcSgs7KeyPathCy13CasePathsCore0S0VyATGA_yqd__GGAXyA0_A_yqd_0_GGAXyA0_A_yqd_1_GGtAY0S8PathableATRQr1_lF::SYNTHESIZED::s:7Lockman0A23DynamicConditionReducerV"},"schemaVersion":{"major":0,"minor":3,"patch":0},"variants":[{"traits":[{"interfaceLanguage":"swift"}],"paths":["\/documentation\/lockman\/lockmandynamicconditionreducer\/lock(boundaryid:unlockoption:lockfailure:for:_:_:)"]}],"sections":[],"kind":"symbol","references":{"doc://Lockman/documentation/Lockman/LockmanBoundaryId":{"url":"\/documentation\/lockman\/lockmanboundaryid","kind":"symbol","identifier":"doc:\/\/Lockman\/documentation\/Lockman\/LockmanBoundaryId","fragments":[{"kind":"keyword","text":"typealias"},{"kind":"text","text":" "},{"kind":"identifier","text":"LockmanBoundaryId"}],"role":"symbol","title":"LockmanBoundaryId","type":"topic","abstract":[{"type":"text","text":"A boundary identifier used by Lockman strategies, combining "},{"type":"codeVoice","code":"Hashable"},{"type":"text","text":" and "},{"type":"codeVoice","code":"Sendable"},{"type":"text","text":" "},{"type":"text","text":"to ensure unique and concurrent-safe keys."}],"navigatorTitle":[{"kind":"identifier","text":"LockmanBoundaryId"}]},"doc://Lockman/documentation/Lockman/LockmanDynamicConditionReducer/Reducer-Implementations":{"kind":"article","type":"topic","role":"collectionGroup","abstract":[],"title":"Reducer Implementations","identifier":"doc:\/\/Lockman\/documentation\/Lockman\/LockmanDynamicConditionReducer\/Reducer-Implementations","url":"\/documentation\/lockman\/lockmandynamicconditionreducer\/reducer-implementations"},"doc://Lockman/documentation/Lockman/LockmanUnlockOption":{"url":"\/documentation\/lockman\/lockmanunlockoption","abstract":[{"text":"Controls when unlock operations are executed.","type":"text"}],"fragments":[{"kind":"keyword","text":"enum"},{"kind":"text","text":" "},{"kind":"identifier","text":"LockmanUnlockOption"}],"identifier":"doc:\/\/Lockman\/documentation\/Lockman\/LockmanUnlockOption","type":"topic","navigatorTitle":[{"kind":"identifier","text":"LockmanUnlockOption"}],"kind":"symbol","role":"symbol","title":"LockmanUnlockOption"},"doc://Lockman/documentation/Lockman/LockmanDynamicConditionReducer":{"abstract":[{"type":"text","text":"A reducer that wraps another reducer with dynamic lock evaluation capabilities."}],"type":"topic","title":"LockmanDynamicConditionReducer","navigatorTitle":[{"text":"LockmanDynamicConditionReducer","kind":"identifier"}],"identifier":"doc:\/\/Lockman\/documentation\/Lockman\/LockmanDynamicConditionReducer","role":"symbol","url":"\/documentation\/lockman\/lockmandynamicconditionreducer","kind":"symbol","fragments":[{"text":"struct","kind":"keyword"},{"text":" ","kind":"text"},{"text":"LockmanDynamicConditionReducer","kind":"identifier"}]},"doc://Lockman/documentation/Lockman/LockmanDynamicConditionReducer/lock(boundaryId:unlockOption:lockFailure:for:_:_:)":{"abstract":[{"text":"Applies Lockman locking to effects with support for nested actions (3 paths).","type":"text"}],"fragments":[{"text":"func","kind":"keyword"},{"text":" ","kind":"text"},{"text":"lock","kind":"identifier"},{"text":"<","kind":"text"},{"text":"Value1","kind":"genericParameter"},{"text":", ","kind":"text"},{"text":"Value2","kind":"genericParameter"},{"text":", ","kind":"text"},{"text":"Value3","kind":"genericParameter"},{"text":">(","kind":"text"},{"text":"boundaryId","kind":"externalParam"},{"text":": any ","kind":"text"},{"text":"LockmanBoundaryId","preciseIdentifier":"s:7Lockman0A10BoundaryIda","kind":"typeIdentifier"},{"text":", ","kind":"text"},{"text":"unlockOption","kind":"externalParam"},{"text":": ","kind":"text"},{"text":"LockmanUnlockOption","preciseIdentifier":"s:7Lockman0A12UnlockOptionO","kind":"typeIdentifier"},{"text":", ","kind":"text"},{"text":"lockFailure","kind":"externalParam"},{"text":": ((any ","kind":"text"},{"text":"Error","preciseIdentifier":"s:s5ErrorP","kind":"typeIdentifier"},{"text":", ","kind":"text"},{"text":"Send","preciseIdentifier":"s:22ComposableArchitecture4SendV","kind":"typeIdentifier"},{"text":"<","kind":"text"},{"text":"Self","kind":"typeIdentifier"},{"text":".","kind":"text"},{"text":"Action","preciseIdentifier":"s:22ComposableArchitecture7ReducerP6ActionQa","kind":"typeIdentifier"},{"text":">) ","kind":"text"},{"text":"async","kind":"keyword"},{"text":" -> ","kind":"text"},{"text":"Void","preciseIdentifier":"s:s4Voida","kind":"typeIdentifier"},{"text":")?, ","kind":"text"},{"text":"for","kind":"externalParam"},{"text":": ","kind":"text"},{"text":"CaseKeyPath","preciseIdentifier":"s:13CasePathsCore0A7KeyPatha","kind":"typeIdentifier"},{"text":"<","kind":"text"},{"text":"Self","kind":"typeIdentifier"},{"text":".","kind":"text"},{"text":"Action","preciseIdentifier":"s:22ComposableArchitecture7ReducerP6ActionQa","kind":"typeIdentifier"},{"text":", ","kind":"text"},{"text":"Value1","kind":"typeIdentifier"},{"text":">, ","kind":"text"},{"text":"CaseKeyPath","preciseIdentifier":"s:13CasePathsCore0A7KeyPatha","kind":"typeIdentifier"},{"text":"<","kind":"text"},{"text":"Self","kind":"typeIdentifier"},{"text":".","kind":"text"},{"text":"Action","preciseIdentifier":"s:22ComposableArchitecture7ReducerP6ActionQa","kind":"typeIdentifier"},{"text":", ","kind":"text"},{"text":"Value2","kind":"typeIdentifier"},{"text":">, ","kind":"text"},{"text":"CaseKeyPath","preciseIdentifier":"s:13CasePathsCore0A7KeyPatha","kind":"typeIdentifier"},{"text":"<","kind":"text"},{"text":"Self","kind":"typeIdentifier"},{"text":".","kind":"text"},{"text":"Action","preciseIdentifier":"s:22ComposableArchitecture7ReducerP6ActionQa","kind":"typeIdentifier"},{"text":", ","kind":"text"},{"text":"Value3","kind":"typeIdentifier"},{"text":">) -> ","kind":"text"},{"text":"LockmanReducer","preciseIdentifier":"s:7Lockman0A7ReducerV","kind":"typeIdentifier"},{"text":"<","kind":"text"},{"text":"Self","kind":"typeIdentifier"},{"text":">","kind":"text"}],"url":"\/documentation\/lockman\/lockmandynamicconditionreducer\/lock(boundaryid:unlockoption:lockfailure:for:_:_:)","kind":"symbol","role":"symbol","type":"topic","identifier":"doc:\/\/Lockman\/documentation\/Lockman\/LockmanDynamicConditionReducer\/lock(boundaryId:unlockOption:lockFailure:for:_:_:)","title":"lock(boundaryId:unlockOption:lockFailure:for:_:_:)"},"doc://Lockman/documentation/Lockman":{"role":"collection","abstract":[{"type":"text","text":"A library to implement exclusive control of user actions in application development using TCA."}],"url":"\/documentation\/lockman","type":"topic","identifier":"doc:\/\/Lockman\/documentation\/Lockman","title":"Lockman","kind":"symbol"},"doc://Lockman/documentation/Lockman/LockmanReducer":{"title":"LockmanReducer","role":"symbol","fragments":[{"text":"struct","kind":"keyword"},{"text":" ","kind":"text"},{"text":"LockmanReducer","kind":"identifier"}],"kind":"symbol","identifier":"doc:\/\/Lockman\/documentation\/Lockman\/LockmanReducer","abstract":[{"text":"A reducer wrapper that applies Lockman locking to effects produced by actions conforming to ","type":"text"},{"code":"LockmanAction","type":"codeVoice"},{"text":".","type":"text"}],"url":"\/documentation\/lockman\/lockmanreducer","type":"topic","navigatorTitle":[{"text":"LockmanReducer","kind":"identifier"}]}}}