{"sections":[],"kind":"symbol","hierarchy":{"paths":[["doc:\/\/Lockman\/documentation\/Lockman","doc:\/\/Lockman\/documentation\/Lockman\/ComposableArchitecture","doc:\/\/Lockman\/documentation\/Lockman\/ComposableArchitecture\/Reducer"]]},"abstract":[{"type":"text","text":"Applies Lockman locking to effects with support for nested actions (4 paths)."}],"primaryContentSections":[{"declarations":[{"languages":["swift"],"platforms":["macOS"],"tokens":[{"text":"func","kind":"keyword"},{"text":" ","kind":"text"},{"text":"lock","kind":"identifier"},{"text":"<","kind":"text"},{"text":"Value1","kind":"genericParameter"},{"text":", ","kind":"text"},{"text":"Value2","kind":"genericParameter"},{"text":", ","kind":"text"},{"text":"Value3","kind":"genericParameter"},{"text":", ","kind":"text"},{"text":"Value4","kind":"genericParameter"},{"text":">(","kind":"text"},{"text":"boundaryId","kind":"externalParam"},{"text":": any ","kind":"text"},{"identifier":"doc:\/\/Lockman\/documentation\/Lockman\/LockmanBoundaryId","text":"LockmanBoundaryId","preciseIdentifier":"s:7Lockman0A10BoundaryIda","kind":"typeIdentifier"},{"text":", ","kind":"text"},{"text":"unlockOption","kind":"externalParam"},{"text":": ","kind":"text"},{"identifier":"doc:\/\/Lockman\/documentation\/Lockman\/LockmanUnlockOption","text":"LockmanUnlockOption","preciseIdentifier":"s:7Lockman0A12UnlockOptionO","kind":"typeIdentifier"},{"text":" = .immediate, ","kind":"text"},{"text":"lockFailure","kind":"externalParam"},{"text":": ((any ","kind":"text"},{"text":"Error","preciseIdentifier":"s:s5ErrorP","kind":"typeIdentifier"},{"text":", ","kind":"text"},{"text":"Send","preciseIdentifier":"s:22ComposableArchitecture4SendV","kind":"typeIdentifier"},{"text":"<","kind":"text"},{"text":"Self","kind":"typeIdentifier"},{"text":".","kind":"text"},{"text":"Action","preciseIdentifier":"s:22ComposableArchitecture7ReducerP6ActionQa","kind":"typeIdentifier"},{"text":">) ","kind":"text"},{"text":"async","kind":"keyword"},{"text":" -> ","kind":"text"},{"text":"Void","preciseIdentifier":"s:s4Voida","kind":"typeIdentifier"},{"text":")? = nil, ","kind":"text"},{"text":"for","kind":"externalParam"},{"text":" ","kind":"text"},{"text":"path1","kind":"internalParam"},{"text":": ","kind":"text"},{"text":"CaseKeyPath","preciseIdentifier":"s:13CasePathsCore0A7KeyPatha","kind":"typeIdentifier"},{"text":"<","kind":"text"},{"text":"Self","kind":"typeIdentifier"},{"text":".","kind":"text"},{"text":"Action","preciseIdentifier":"s:22ComposableArchitecture7ReducerP6ActionQa","kind":"typeIdentifier"},{"text":", ","kind":"text"},{"text":"Value1","kind":"typeIdentifier"},{"text":">, ","kind":"text"},{"text":"_","kind":"externalParam"},{"text":" ","kind":"text"},{"text":"path2","kind":"internalParam"},{"text":": ","kind":"text"},{"text":"CaseKeyPath","preciseIdentifier":"s:13CasePathsCore0A7KeyPatha","kind":"typeIdentifier"},{"text":"<","kind":"text"},{"text":"Self","kind":"typeIdentifier"},{"text":".","kind":"text"},{"text":"Action","preciseIdentifier":"s:22ComposableArchitecture7ReducerP6ActionQa","kind":"typeIdentifier"},{"text":", ","kind":"text"},{"text":"Value2","kind":"typeIdentifier"},{"text":">, ","kind":"text"},{"text":"_","kind":"externalParam"},{"text":" ","kind":"text"},{"text":"path3","kind":"internalParam"},{"text":": ","kind":"text"},{"text":"CaseKeyPath","preciseIdentifier":"s:13CasePathsCore0A7KeyPatha","kind":"typeIdentifier"},{"text":"<","kind":"text"},{"text":"Self","kind":"typeIdentifier"},{"text":".","kind":"text"},{"text":"Action","preciseIdentifier":"s:22ComposableArchitecture7ReducerP6ActionQa","kind":"typeIdentifier"},{"text":", ","kind":"text"},{"text":"Value3","kind":"typeIdentifier"},{"text":">, ","kind":"text"},{"text":"_","kind":"externalParam"},{"text":" ","kind":"text"},{"text":"path4","kind":"internalParam"},{"text":": ","kind":"text"},{"text":"CaseKeyPath","preciseIdentifier":"s:13CasePathsCore0A7KeyPatha","kind":"typeIdentifier"},{"text":"<","kind":"text"},{"text":"Self","kind":"typeIdentifier"},{"text":".","kind":"text"},{"text":"Action","preciseIdentifier":"s:22ComposableArchitecture7ReducerP6ActionQa","kind":"typeIdentifier"},{"text":", ","kind":"text"},{"text":"Value4","kind":"typeIdentifier"},{"text":">) -> ","kind":"text"},{"identifier":"doc:\/\/Lockman\/documentation\/Lockman\/LockmanReducer","text":"LockmanReducer","preciseIdentifier":"s:7Lockman0A7ReducerV","kind":"typeIdentifier"},{"text":"<","kind":"text"},{"text":"Self","kind":"typeIdentifier"},{"text":"> ","kind":"text"},{"text":"where","kind":"keyword"},{"text":" ","kind":"text"},{"text":"Self","kind":"typeIdentifier"},{"text":".","kind":"text"},{"text":"Action","preciseIdentifier":"s:22ComposableArchitecture7ReducerP6ActionQa","kind":"typeIdentifier"},{"text":" : ","kind":"text"},{"text":"CasePathable","preciseIdentifier":"s:13CasePathsCore0A8PathableP","kind":"typeIdentifier"}]}],"kind":"declarations"},{"parameters":[{"name":"boundaryId","content":[{"inlineContent":[{"text":"The boundary identifier for locking.","type":"text"}],"type":"paragraph"}]},{"name":"unlockOption","content":[{"type":"paragraph","inlineContent":[{"text":"When to release the lock. Defaults to ","type":"text"},{"type":"codeVoice","code":".immediate"},{"text":".","type":"text"}]}]},{"name":"lockFailure","content":[{"type":"paragraph","inlineContent":[{"text":"Optional callback invoked when lock acquisition fails.","type":"text"}]}]},{"name":"path1","content":[{"inlineContent":[{"type":"text","text":"First case path to extract a nested action."}],"type":"paragraph"}]},{"name":"path2","content":[{"inlineContent":[{"type":"text","text":"Second case path to extract a nested action."}],"type":"paragraph"}]},{"name":"path3","content":[{"type":"paragraph","inlineContent":[{"text":"Third case path to extract a nested action.","type":"text"}]}]},{"name":"path4","content":[{"type":"paragraph","inlineContent":[{"text":"Fourth case path to extract a nested action.","type":"text"}]}]}],"kind":"parameters"},{"content":[{"anchor":"return-value","text":"Return Value","type":"heading","level":2},{"inlineContent":[{"text":"A ","type":"text"},{"code":"LockmanReducer","type":"codeVoice"},{"text":" that wraps this reducer with locking behavior.","type":"text"}],"type":"paragraph"}],"kind":"content"},{"content":[{"type":"heading","anchor":"discussion","level":2,"text":"Discussion"},{"inlineContent":[{"type":"text","text":"This overload supports the ViewAction pattern in TCA where actions may be nested"},{"type":"text","text":" "},{"type":"text","text":"within enum cases. It checks both the root action and the specified nested paths."}],"type":"paragraph"}],"kind":"content"}],"metadata":{"roleHeading":"Instance Method","externalID":"s:22ComposableArchitecture7ReducerP7LockmanE4lock10boundaryId12unlockOption0E7Failure3for___AD0dC0VyxGSH_s8Sendablep_AD0d6UnlockI0Oys5Error_p_AA4SendVy6ActionQzGtYaYbcSgs7KeyPathCy13CasePathsCore0S0VyATGA_yqd__GGAXyA0_A_yqd_0_GGAXyA0_A_yqd_1_GGAXyA0_A_yqd_2_GGtAY0S8PathableATRQr2_lF","role":"symbol","fragments":[{"kind":"keyword","text":"func"},{"kind":"text","text":" "},{"kind":"identifier","text":"lock"},{"kind":"text","text":"<"},{"kind":"genericParameter","text":"Value1"},{"kind":"text","text":", "},{"kind":"genericParameter","text":"Value2"},{"kind":"text","text":", "},{"kind":"genericParameter","text":"Value3"},{"kind":"text","text":", "},{"kind":"genericParameter","text":"Value4"},{"kind":"text","text":">("},{"kind":"externalParam","text":"boundaryId"},{"kind":"text","text":": any "},{"preciseIdentifier":"s:7Lockman0A10BoundaryIda","kind":"typeIdentifier","text":"LockmanBoundaryId"},{"kind":"text","text":", "},{"kind":"externalParam","text":"unlockOption"},{"kind":"text","text":": "},{"preciseIdentifier":"s:7Lockman0A12UnlockOptionO","kind":"typeIdentifier","text":"LockmanUnlockOption"},{"kind":"text","text":", "},{"kind":"externalParam","text":"lockFailure"},{"kind":"text","text":": ((any "},{"kind":"typeIdentifier","preciseIdentifier":"s:s5ErrorP","text":"Error"},{"kind":"text","text":", "},{"kind":"typeIdentifier","preciseIdentifier":"s:22ComposableArchitecture4SendV","text":"Send"},{"kind":"text","text":"<"},{"kind":"typeIdentifier","text":"Self"},{"kind":"text","text":"."},{"kind":"typeIdentifier","preciseIdentifier":"s:22ComposableArchitecture7ReducerP6ActionQa","text":"Action"},{"kind":"text","text":">) "},{"kind":"keyword","text":"async"},{"kind":"text","text":" -> "},{"kind":"typeIdentifier","preciseIdentifier":"s:s4Voida","text":"Void"},{"kind":"text","text":")?, "},{"kind":"externalParam","text":"for"},{"kind":"text","text":": "},{"kind":"typeIdentifier","preciseIdentifier":"s:13CasePathsCore0A7KeyPatha","text":"CaseKeyPath"},{"kind":"text","text":"<"},{"kind":"typeIdentifier","text":"Self"},{"kind":"text","text":"."},{"kind":"typeIdentifier","preciseIdentifier":"s:22ComposableArchitecture7ReducerP6ActionQa","text":"Action"},{"kind":"text","text":", "},{"kind":"typeIdentifier","text":"Value1"},{"kind":"text","text":">, "},{"kind":"typeIdentifier","preciseIdentifier":"s:13CasePathsCore0A7KeyPatha","text":"CaseKeyPath"},{"kind":"text","text":"<"},{"kind":"typeIdentifier","text":"Self"},{"kind":"text","text":"."},{"kind":"typeIdentifier","preciseIdentifier":"s:22ComposableArchitecture7ReducerP6ActionQa","text":"Action"},{"kind":"text","text":", "},{"kind":"typeIdentifier","text":"Value2"},{"kind":"text","text":">, "},{"kind":"typeIdentifier","preciseIdentifier":"s:13CasePathsCore0A7KeyPatha","text":"CaseKeyPath"},{"kind":"text","text":"<"},{"kind":"typeIdentifier","text":"Self"},{"kind":"text","text":"."},{"kind":"typeIdentifier","preciseIdentifier":"s:22ComposableArchitecture7ReducerP6ActionQa","text":"Action"},{"kind":"text","text":", "},{"kind":"typeIdentifier","text":"Value3"},{"kind":"text","text":">, "},{"kind":"typeIdentifier","preciseIdentifier":"s:13CasePathsCore0A7KeyPatha","text":"CaseKeyPath"},{"kind":"text","text":"<"},{"kind":"typeIdentifier","text":"Self"},{"kind":"text","text":"."},{"kind":"typeIdentifier","preciseIdentifier":"s:22ComposableArchitecture7ReducerP6ActionQa","text":"Action"},{"kind":"text","text":", "},{"kind":"typeIdentifier","text":"Value4"},{"kind":"text","text":">) -> "},{"kind":"typeIdentifier","preciseIdentifier":"s:7Lockman0A7ReducerV","text":"LockmanReducer"},{"kind":"text","text":"<"},{"kind":"typeIdentifier","text":"Self"},{"kind":"text","text":">"}],"modules":[{"relatedModules":["ComposableArchitecture"],"name":"Lockman"}],"title":"lock(boundaryId:unlockOption:lockFailure:for:_:_:_:)","symbolKind":"method","extendedModule":"ComposableArchitecture"},"schemaVersion":{"patch":0,"minor":3,"major":0},"variants":[{"traits":[{"interfaceLanguage":"swift"}],"paths":["\/documentation\/lockman\/composablearchitecture\/reducer\/lock(boundaryid:unlockoption:lockfailure:for:_:_:_:)"]}],"identifier":{"url":"doc:\/\/Lockman\/documentation\/Lockman\/ComposableArchitecture\/Reducer\/lock(boundaryId:unlockOption:lockFailure:for:_:_:_:)","interfaceLanguage":"swift"},"references":{"doc://Lockman/documentation/Lockman/ComposableArchitecture/Reducer":{"kind":"symbol","title":"Reducer","identifier":"doc:\/\/Lockman\/documentation\/Lockman\/ComposableArchitecture\/Reducer","role":"symbol","fragments":[{"text":"extension","kind":"keyword"},{"text":" ","kind":"text"},{"text":"Reducer","preciseIdentifier":"s:22ComposableArchitecture7ReducerP","kind":"identifier"}],"navigatorTitle":[{"text":"Reducer","kind":"identifier"}],"type":"topic","abstract":[],"url":"\/documentation\/lockman\/composablearchitecture\/reducer"},"doc://Lockman/documentation/Lockman/LockmanUnlockOption":{"navigatorTitle":[{"kind":"identifier","text":"LockmanUnlockOption"}],"identifier":"doc:\/\/Lockman\/documentation\/Lockman\/LockmanUnlockOption","type":"topic","url":"\/documentation\/lockman\/lockmanunlockoption","title":"LockmanUnlockOption","abstract":[{"type":"text","text":"Controls when unlock operations are executed."}],"kind":"symbol","fragments":[{"text":"enum","kind":"keyword"},{"kind":"text","text":" "},{"kind":"identifier","text":"LockmanUnlockOption"}],"role":"symbol"},"doc://Lockman/documentation/Lockman/LockmanBoundaryId":{"kind":"symbol","abstract":[{"type":"text","text":"A protocol composition for boundary identifiers used by Lockman strategies."}],"identifier":"doc:\/\/Lockman\/documentation\/Lockman\/LockmanBoundaryId","title":"LockmanBoundaryId","url":"\/documentation\/lockman\/lockmanboundaryid","role":"symbol","fragments":[{"kind":"keyword","text":"typealias"},{"kind":"text","text":" "},{"kind":"identifier","text":"LockmanBoundaryId"}],"type":"topic","navigatorTitle":[{"kind":"identifier","text":"LockmanBoundaryId"}]},"doc://Lockman/documentation/Lockman/ComposableArchitecture/Reducer/lock(boundaryId:unlockOption:lockFailure:for:_:_:_:)":{"kind":"symbol","role":"symbol","title":"lock(boundaryId:unlockOption:lockFailure:for:_:_:_:)","identifier":"doc:\/\/Lockman\/documentation\/Lockman\/ComposableArchitecture\/Reducer\/lock(boundaryId:unlockOption:lockFailure:for:_:_:_:)","fragments":[{"kind":"keyword","text":"func"},{"kind":"text","text":" "},{"kind":"identifier","text":"lock"},{"kind":"text","text":"<"},{"kind":"genericParameter","text":"Value1"},{"kind":"text","text":", "},{"kind":"genericParameter","text":"Value2"},{"kind":"text","text":", "},{"kind":"genericParameter","text":"Value3"},{"kind":"text","text":", "},{"kind":"genericParameter","text":"Value4"},{"kind":"text","text":">("},{"kind":"externalParam","text":"boundaryId"},{"kind":"text","text":": any "},{"kind":"typeIdentifier","text":"LockmanBoundaryId","preciseIdentifier":"s:7Lockman0A10BoundaryIda"},{"kind":"text","text":", "},{"kind":"externalParam","text":"unlockOption"},{"kind":"text","text":": "},{"kind":"typeIdentifier","text":"LockmanUnlockOption","preciseIdentifier":"s:7Lockman0A12UnlockOptionO"},{"kind":"text","text":", "},{"kind":"externalParam","text":"lockFailure"},{"kind":"text","text":": ((any "},{"kind":"typeIdentifier","text":"Error","preciseIdentifier":"s:s5ErrorP"},{"kind":"text","text":", "},{"kind":"typeIdentifier","text":"Send","preciseIdentifier":"s:22ComposableArchitecture4SendV"},{"kind":"text","text":"<"},{"kind":"typeIdentifier","text":"Self"},{"kind":"text","text":"."},{"kind":"typeIdentifier","text":"Action","preciseIdentifier":"s:22ComposableArchitecture7ReducerP6ActionQa"},{"kind":"text","text":">) "},{"kind":"keyword","text":"async"},{"kind":"text","text":" -> "},{"kind":"typeIdentifier","text":"Void","preciseIdentifier":"s:s4Voida"},{"kind":"text","text":")?, "},{"kind":"externalParam","text":"for"},{"kind":"text","text":": "},{"kind":"typeIdentifier","text":"CaseKeyPath","preciseIdentifier":"s:13CasePathsCore0A7KeyPatha"},{"kind":"text","text":"<"},{"kind":"typeIdentifier","text":"Self"},{"kind":"text","text":"."},{"kind":"typeIdentifier","text":"Action","preciseIdentifier":"s:22ComposableArchitecture7ReducerP6ActionQa"},{"kind":"text","text":", "},{"kind":"typeIdentifier","text":"Value1"},{"kind":"text","text":">, "},{"kind":"typeIdentifier","text":"CaseKeyPath","preciseIdentifier":"s:13CasePathsCore0A7KeyPatha"},{"kind":"text","text":"<"},{"kind":"typeIdentifier","text":"Self"},{"kind":"text","text":"."},{"kind":"typeIdentifier","text":"Action","preciseIdentifier":"s:22ComposableArchitecture7ReducerP6ActionQa"},{"kind":"text","text":", "},{"kind":"typeIdentifier","text":"Value2"},{"kind":"text","text":">, "},{"kind":"typeIdentifier","text":"CaseKeyPath","preciseIdentifier":"s:13CasePathsCore0A7KeyPatha"},{"kind":"text","text":"<"},{"kind":"typeIdentifier","text":"Self"},{"kind":"text","text":"."},{"kind":"typeIdentifier","text":"Action","preciseIdentifier":"s:22ComposableArchitecture7ReducerP6ActionQa"},{"kind":"text","text":", "},{"kind":"typeIdentifier","text":"Value3"},{"kind":"text","text":">, "},{"kind":"typeIdentifier","text":"CaseKeyPath","preciseIdentifier":"s:13CasePathsCore0A7KeyPatha"},{"kind":"text","text":"<"},{"kind":"typeIdentifier","text":"Self"},{"kind":"text","text":"."},{"kind":"typeIdentifier","text":"Action","preciseIdentifier":"s:22ComposableArchitecture7ReducerP6ActionQa"},{"kind":"text","text":", "},{"kind":"typeIdentifier","text":"Value4"},{"kind":"text","text":">) -> "},{"kind":"typeIdentifier","text":"LockmanReducer","preciseIdentifier":"s:7Lockman0A7ReducerV"},{"kind":"text","text":"<"},{"kind":"typeIdentifier","text":"Self"},{"kind":"text","text":">"}],"type":"topic","abstract":[{"text":"Applies Lockman locking to effects with support for nested actions (4 paths).","type":"text"}],"url":"\/documentation\/lockman\/composablearchitecture\/reducer\/lock(boundaryid:unlockoption:lockfailure:for:_:_:_:)"},"doc://Lockman/documentation/Lockman":{"identifier":"doc:\/\/Lockman\/documentation\/Lockman","type":"topic","url":"\/documentation\/lockman","abstract":[{"type":"text","text":"Elegant exclusive control for user actions in The Composable Architecture applications."}],"title":"Lockman","kind":"symbol","role":"collection"},"doc://Lockman/documentation/Lockman/ComposableArchitecture":{"role":"collection","abstract":[],"title":"ComposableArchitecture","kind":"symbol","url":"\/documentation\/lockman\/composablearchitecture","identifier":"doc:\/\/Lockman\/documentation\/Lockman\/ComposableArchitecture","type":"topic"},"doc://Lockman/documentation/Lockman/LockmanReducer":{"type":"topic","role":"symbol","identifier":"doc:\/\/Lockman\/documentation\/Lockman\/LockmanReducer","abstract":[{"type":"text","text":"A reducer wrapper that applies Lockman locking with true lock-first behavior."}],"kind":"symbol","fragments":[{"kind":"keyword","text":"struct"},{"kind":"text","text":" "},{"kind":"identifier","text":"LockmanReducer"}],"navigatorTitle":[{"kind":"identifier","text":"LockmanReducer"}],"title":"LockmanReducer","url":"\/documentation\/lockman\/lockmanreducer"}}}